HulianwangJavaGongchengshiJinjieZhishiWanquanSaomangFix1/README.md
HulianwangJavaGongchengshiJinjieZhishiWanquanSaomangFix1/__init__.py
HulianwangJavaGongchengshiJinjieZhishiWanquanSaomangFix1/__main__.py
HulianwangJavaGongchengshiJinjieZhishiWanquanSaomangFix1/file.epub
HulianwangJavaGongchengshiJinjieZhishiWanquanSaomangFix1/index.html
HulianwangJavaGongchengshiJinjieZhishiWanquanSaomangFix1/css/__init__.py
HulianwangJavaGongchengshiJinjieZhishiWanquanSaomangFix1/css/annotations.css
HulianwangJavaGongchengshiJinjieZhishiWanquanSaomangFix1/css/main.css
HulianwangJavaGongchengshiJinjieZhishiWanquanSaomangFix1/css/normalize.css
HulianwangJavaGongchengshiJinjieZhishiWanquanSaomangFix1/css/popup.css
HulianwangJavaGongchengshiJinjieZhishiWanquanSaomangFix1/font/__init__.py
HulianwangJavaGongchengshiJinjieZhishiWanquanSaomangFix1/font/fontello.eot
HulianwangJavaGongchengshiJinjieZhishiWanquanSaomangFix1/font/fontello.svg
HulianwangJavaGongchengshiJinjieZhishiWanquanSaomangFix1/font/fontello.ttf
HulianwangJavaGongchengshiJinjieZhishiWanquanSaomangFix1/font/fontello.woff
HulianwangJavaGongchengshiJinjieZhishiWanquanSaomangFix1/img/__init__.py
HulianwangJavaGongchengshiJinjieZhishiWanquanSaomangFix1/img/annotator-glyph-sprite.png
HulianwangJavaGongchengshiJinjieZhishiWanquanSaomangFix1/img/annotator-icon-sprite.png
HulianwangJavaGongchengshiJinjieZhishiWanquanSaomangFix1/img/apple-touch-icon.png
HulianwangJavaGongchengshiJinjieZhishiWanquanSaomangFix1/img/cancelfullscreen.png
HulianwangJavaGongchengshiJinjieZhishiWanquanSaomangFix1/img/close.png
HulianwangJavaGongchengshiJinjieZhishiWanquanSaomangFix1/img/fullscreen.png
HulianwangJavaGongchengshiJinjieZhishiWanquanSaomangFix1/img/loader.gif
HulianwangJavaGongchengshiJinjieZhishiWanquanSaomangFix1/img/menu-icon.png
HulianwangJavaGongchengshiJinjieZhishiWanquanSaomangFix1/img/save.png
HulianwangJavaGongchengshiJinjieZhishiWanquanSaomangFix1/img/saved.png
hulianwang_java_gongchengshi_jinjie_zhishi_wanquan_saomang_fix1-2025.3.25.1.dist-info/METADATA
hulianwang_java_gongchengshi_jinjie_zhishi_wanquan_saomang_fix1-2025.3.25.1.dist-info/WHEEL
hulianwang_java_gongchengshi_jinjie_zhishi_wanquan_saomang_fix1-2025.3.25.1.dist-info/entry_points.txt
hulianwang_java_gongchengshi_jinjie_zhishi_wanquan_saomang_fix1-2025.3.25.1.dist-info/top_level.txt
hulianwang_java_gongchengshi_jinjie_zhishi_wanquan_saomang_fix1-2025.3.25.1.dist-info/RECORD
